README.rst
setup.py
django_translation_client.egg-info/PKG-INFO
django_translation_client.egg-info/SOURCES.txt
django_translation_client.egg-info/dependency_links.txt
django_translation_client.egg-info/requires.txt
django_translation_client.egg-info/top_level.txt
translation_client/__init__.py
translation_client/admin.py
translation_client/apps.py
translation_client/exceptions.py
translation_client/models.py
translation_client/tests.py
translation_client/views.py
translation_client/management/__init__.py
translation_client/management/tests.py
translation_client/management/commands/__init__.py
translation_client/management/commands/sync_translations.py
translation_client/migrations/__init__.py