Metadata-Version: 1.1
Name: django-translation-client
Version: 0.3.4
Summary: Django translation client
Home-page: https://github.com/gdelnegro/django-translation-client
Author: Gustavo Del Negro
Author-email: gustavodelnegro@gmail.com
License: MIT
Platform: UNKNOWN
Classifier: Development Status :: 4 - Beta
Classifier: Environment :: Web Environment
Classifier: Framework :: Django
Classifier: Framework :: Django :: 1.9
Classifier: Intended Audience :: Developers
Classifier: License :: OSI Approved :: MIT License
Classifier: Operating System :: OS Independent
Classifier: Programming Language :: Python
Classifier: Programming Language :: Python :: 3
Classifier: Programming Language :: Python :: 3.4
Classifier: Programming Language :: Python :: 3.5
